llm_gpt4all.py
llm_gpt4all-0.4.dist-info/LICENSE
llm_gpt4all-0.4.dist-info/METADATA
llm_gpt4all-0.4.dist-info/WHEEL
llm_gpt4all-0.4.dist-info/entry_points.txt
llm_gpt4all-0.4.dist-info/top_level.txt
llm_gpt4all-0.4.dist-info/RECORD
