Metadata-Version: 2.1
Name: llm-gpt4all
Version: 0.4
Summary: Plugin for LLM adding support for GPT4ALL models
Home-page: https://github.com/simonw/llm-gpt4all
Author: Simon Willison
License: Apache License, Version 2.0
Project-URL: Issues, https://github.com/simonw/llm-gpt4all/issues
Project-URL: CI, https://github.com/simonw/llm-gpt4all/actions
Project-URL: Changelog, https://github.com/simonw/llm-gpt4all/releases
Classifier: License :: OSI Approved :: Apache Software License
Requires-Python: >=3.9
License-File: LICENSE
Requires-Dist: llm >=0.11
Requires-Dist: gpt4all >=2.5.1
Requires-Dist: httpx
Provides-Extra: test
Requires-Dist: pytest ; extra == 'test'
